{
    "name": "zby",
    "keyboardType": 3,
    "seconds": 204.693161,
    "phraseLength": 153,
    "phrases": [
        "this camera takes nice photographs",
        "prepare for the exam in advance",
        "dashing through the snow",
        "my favorite subject is psychology",
        "this library has many books"
    ],
    "result": "this camera takes nice photographs\nprepare for the exam in advance\ndashing through the snow \nmy favorite subject is psychology \nthis library has many books ",
    "totalErr": 78,
    "ncErr": 64,
    "WPM": 8.969522,
    "TER": 0.1437908496732026,
    "NCER": 0.0,
    "theta": 0.37,
    "r": 7.8,
    "firstTouches": [
        {
            "key": "t",
            "lr": 1,
            "x": -0.896694839,
            "y": -0.0541398376
        },
        {
            "key": "h",
            "lr": 1,
            "x": -0.3010956,
            "y": -0.235663936
        },
        {
            "key": "i",
            "lr": 1,
            "x": -0.204351917,
            "y": 0.0413831
        },
        {
            "key": "c",
            "lr": 1,
            "x": -0.290108949,
            "y": -0.5541551
        },
        {
            "key": "a",
            "lr": 0,
            "x": -0.989654243,
            "y": 0.143681139
        },
        {
            "key": "m",
            "lr": 1,
            "x": 0.7956175,
            "y": -0.1528367
        },
        {
            "key": "e",
            "lr": 0,
            "x": -0.210943937,
            "y": 0.286629856
        },
        {
            "key": "r",
            "lr": 0,
            "x": 0.210943937,
            "y": 0.108279675
        },
        {
            "key": "a",
            "lr": 0,
            "x": -0.997772157,
            "y": 0.0445570238
        },
        {
            "key": " ",
            "lr": 1,
            "x": -0.200811788,
            "y": -0.9796442
        },
        {
            "key": "t",
            "lr": 1,
            "x": -0.67030853,
            "y": -0.4076052
        },
        {
            "key": "a",
            "lr": 0,
            "x": -0.9692068,
            "y": 0.2451857
        },
        {
            "key": "k",
            "lr": 1,
            "x": -0.166997284,
            "y": -0.328012943
        },
        {
            "key": "e",
            "lr": 0,
            "x": -0.164799958,
            "y": 0.0445570238
        },
        {
            "key": "s",
            "lr": 0,
            "x": -0.6549272,
            "y": -0.07959227
        },
        {
            "key": " ",
            "lr": 1,
            "x": -0.4680929,
            "y": -0.882168055
        },
        {
            "key": "n",
            "lr": 1,
            "x": -0.501113951,
            "y": -0.324839026
        },
        {
            "key": "i",
            "lr": 1,
            "x": -0.0153813288,
            "y": -0.337534726
        },
        {
            "key": "c",
            "lr": 1,
            "x": 0.12305063,
            "y": 0.14007996
        },
        {
            "key": "p",
            "lr": 1,
            "x": -0.3670156,
            "y": -0.136906028
        },
        {
            "key": "h",
            "lr": 1,
            "x": 0.3340556,
            "y": 0.3566393
        },
        {
            "key": "o",
            "lr": 1,
            "x": -0.5121006,
            "y": -0.159184545
        },
        {
            "key": "t",
            "lr": 1,
            "x": -0.67030853,
            "y": 0.17828913
        },
        {
            "key": "o",
            "lr": 1,
            "x": 0.4153569,
            "y": 0.5254677
        },
        {
            "key": "g",
            "lr": 1,
            "x": 0.320871621,
            "y": 0.187871948
        },
        {
            "key": "r",
            "lr": 0,
            "x": 0.0856959745,
            "y": -0.22925505
        },
        {
            "key": "a",
            "lr": 0,
            "x": -0.8703269,
            "y": 0.09552293
        },
        {
            "key": "\n",
            "lr": 1,
            "x": 0.6571245,
            "y": 0.640095234
        },
        {
            "key": "s",
            "lr": 0,
            "x": -0.5142979,
            "y": 0.114627525
        },
        {
            "key": "\n",
            "lr": 1,
            "x": 0.643940568,
            "y": -0.6178167
        },
        {
            "key": "p",
            "lr": 1,
            "x": 0.204351917,
            "y": 0.452223271
        },
        {
            "key": "r",
            "lr": 0,
            "x": 0.08130131,
            "y": 0.2451857
        },
        {
            "key": "e",
            "lr": 1,
            "x": 0.4395886,
            "y": 0.8982208
        },
        {
            "key": "r",
            "lr": 0,
            "x": 0.160405263,
            "y": 0.257942438
        },
        {
            "key": "e",
            "lr": 0,
            "x": -0.195562586,
            "y": 0.398083448
        },
        {
            "key": "p",
            "lr": 0,
            "x": 0.2725303,
            "y": 0.09552293
        },
        {
            "key": "a",
            "lr": 1,
            "x": 0.4395886,
            "y": 0.8982208
        },
        {
            "key": "p",
            "lr": 1,
            "x": 0.7641224,
            "y": 0.64491713
        },
        {
            "key": "a",
            "lr": 0,
            "x": -0.9696951,
            "y": 0.2445143
        },
        {
            "key": "r",
            "lr": 0,
            "x": 0.145023957,
            "y": 0.09552293
        },
        {
            "key": "e",
            "lr": 0,
            "x": -0.116458632,
            "y": 0.162419513
        },
        {
            "key": " ",
            "lr": 1,
            "x": -0.175786614,
            "y": -0.4267098
        },
        {
            "key": "f",
            "lr": 0,
            "x": 0.254951626,
            "y": -0.0413831
        },
        {
            "key": "o",
            "lr": 1,
            "x": 0.7714469,
            "y": 0.630573452
        },
        {
            "key": "r",
            "lr": 0,
            "x": 0.2417066,
            "y": -0.003173925
        },
        {
            "key": " ",
            "lr": 1,
            "x": 0.008789331,
            "y": -0.60506
        },
        {
            "key": "t",
            "lr": 1,
            "x": -0.382396936,
            "y": -0.0445570238
        },
        {
            "key": "h",
            "lr": 1,
            "x": -0.628559232,
            "y": 0.06683554
        },
        {
            "key": "e",
            "lr": 0,
            "x": -0.0285653248,
            "y": 0.09552293
        },
        {
            "key": " ",
            "lr": 1,
            "x": -0.112063967,
            "y": -0.9203772
        },
        {
            "key": "e",
            "lr": 0,
            "x": 0.08825953,
            "y": 0.197454751
        },
        {
            "key": "x",
            "lr": 0,
            "x": -0.4219489,
            "y": -0.222907171
        },
        {
            "key": "a",
            "lr": 0,
            "x": -0.9164708,
            "y": 0.324839026
        },
        {
            "key": "m",
            "lr": 1,
            "x": 0.408764929,
            "y": -0.254768521
        },
        {
            "key": " ",
            "lr": 1,
            "x": 0.0153813288,
            "y": -0.984099865
        },
        {
            "key": "i",
            "lr": 1,
            "x": -0.2021546,
            "y": -0.3439436
        },
        {
            "key": "n",
            "lr": 1,
            "x": 0.371410251,
            "y": -0.3439436
        },
        {
            "key": " ",
            "lr": 1,
            "x": -0.0153813288,
            "y": -0.9904477
        },
        {
            "key": "a",
            "lr": 0,
            "x": -0.8988311,
            "y": 0.4450209
        },
        {
            "key": "d",
            "lr": 0,
            "x": -0.03295999,
            "y": 0.09552293
        },
        {
            "key": "v",
            "lr": 0,
            "x": 0.221930578,
            "y": -0.5318155
        },
        {
            "key": "a",
            "lr": 0,
            "x": -0.8593402,
            "y": 0.4331187
        },
        {
            "key": "n",
            "lr": 1,
            "x": 0.419751585,
            "y": -0.283394873
        },
        {
            "key": "c",
            "lr": 0,
            "x": -0.08789331,
            "y": -0.06366161
        },
        {
            "key": "c",
            "lr": 0,
            "x": -0.379520446,
            "y": 0.0237627365
        },
        {
            "key": "e",
            "lr": 1,
            "x": 0.497024447,
            "y": 0.867702246
        },
        {
            "key": "c",
            "lr": 1,
            "x": -0.0175786614,
            "y": -0.923551142
        },
        {
            "key": "e",
            "lr": 0,
            "x": -0.175786614,
            "y": 0.222907171
        },
        {
            "key": "\n",
            "lr": 1,
            "x": 0.7230445,
            "y": -0.302499473
        },
        {
            "key": "d",
            "lr": 0,
            "x": -0.3054903,
            "y": 0.219733268
        },
        {
            "key": "a",
            "lr": 0,
            "x": -0.8791162,
            "y": 0.280220956
        },
        {
            "key": "s",
            "lr": 0,
            "x": -0.424146235,
            "y": 0.175115213
        },
        {
            "key": "h",
            "lr": 1,
            "x": -0.1691946,
            "y": -0.00634785
        },
        {
            "key": "i",
            "lr": 1,
            "x": 0.0593279824,
            "y": 0.410840183
        },
        {
            "key": "n",
            "lr": 1,
            "x": 0.470290244,
            "y": -0.2961516
        },
        {
            "key": "g",
            "lr": 1,
            "x": -0.496658236,
            "y": -0.270699173
        },
        {
            "key": " ",
            "lr": 1,
            "x": -0.1142613,
            "y": -0.984099865
        },
        {
            "key": "t",
            "lr": 1,
            "x": -0.90987885,
            "y": -0.117801435
        },
        {
            "key": "h",
            "lr": 1,
            "x": -0.417554259,
            "y": -0.0445570238
        },
        {
            "key": "r",
            "lr": 1,
            "x": -0.09009064,
            "y": -0.187871948
        },
        {
            "key": "o",
            "lr": 1,
            "x": 0.302011162,
            "y": 0.9533372
        },
        {
            "key": "r",
            "lr": 0,
            "x": 0.1208533,
            "y": 0.00634785
        },
        {
            "key": "o",
            "lr": 1,
            "x": 0.103274636,
            "y": 0.3566393
        },
        {
            "key": "u",
            "lr": 1,
            "x": -0.2351146,
            "y": -0.2961516
        },
        {
            "key": "g",
            "lr": 1,
            "x": -0.443922251,
            "y": -0.117801435
        },
        {
            "key": "h",
            "lr": 1,
            "x": -0.158207953,
            "y": -0.07641835
        },
        {
            "key": "t",
            "lr": 1,
            "x": -0.457106233,
            "y": -0.283394873
        },
        {
            "key": "h",
            "lr": 1,
            "x": -0.6263619,
            "y": 0.0254524369
        },
        {
            "key": "e",
            "lr": 0,
            "x": -0.0263679922,
            "y": 0.227546
        },
        {
            "key": " ",
            "lr": 1,
            "x": -0.03295999,
            "y": -0.8089236
        },
        {
            "key": "s",
            "lr": 0,
            "x": -0.384594262,
            "y": 0.120975375
        },
        {
            "key": "n",
            "lr": 1,
            "x": 0.173589289,
            "y": -0.21015045
        },
        {
            "key": "o",
            "lr": 1,
            "x": 0.26947844,
            "y": 0.9630421
        },
        {
            "key": "n",
            "lr": 1,
            "x": 0.171391949,
            "y": -0.184698015
        },
        {
            "key": "o",
            "lr": 1,
            "x": 0.03955199,
            "y": 0.4267098
        },
        {
            "key": "w",
            "lr": 0,
            "x": -0.250556976,
            "y": 0.410840183
        },
        {
            "key": "\n",
            "lr": 1,
            "x": -0.128299817,
            "y": -0.9917295
        },
        {
            "key": "m",
            "lr": 1,
            "x": 0.705465853,
            "y": -0.5732597
        },
        {
            "key": "y",
            "lr": 1,
            "x": 0.2791223,
            "y": 0.0382091738
        },
        {
            "key": " ",
            "lr": 1,
            "x": 0.367076635,
            "y": 0.930204153
        },
        {
            "key": "y",
            "lr": 1,
            "x": 0.408764929,
            "y": -0.09552293
        },
        {
            "key": " ",
            "lr": 1,
            "x": -0.2527543,
            "y": 0.404431283
        },
        {
            "key": "f",
            "lr": 1,
            "x": -0.1076693,
            "y": -0.662434757
        },
        {
            "key": "a",
            "lr": 0,
            "x": 0.18018128,
            "y": -0.175115213
        },
        {
            "key": "v",
            "lr": 0,
            "x": -0.9120762,
            "y": 0.2515946
        },
        {
            "key": "o",
            "lr": 0,
            "x": 0.270332962,
            "y": -0.6751305
        },
        {
            "key": "r",
            "lr": 1,
            "x": 0.529679239,
            "y": 0.601886034
        },
        {
            "key": "i",
            "lr": 1,
            "x": 0.03955199,
            "y": -0.117801435
        },
        {
            "key": "t",
            "lr": 1,
            "x": 0.5721,
            "y": 0.820215464
        },
        {
            "key": "e",
            "lr": 1,
            "x": 0.3106174,
            "y": 0.950590551
        },
        {
            "key": "t",
            "lr": 1,
            "x": 0.253791928,
            "y": 0.967314661
        },
        {
            "key": "i",
            "lr": 0,
            "x": 0.435132921,
            "y": 0.14007996
        },
        {
            "key": "t",
            "lr": 1,
            "x": 0.419568479,
            "y": 0.90774256
        },
        {
            "key": "i",
            "lr": 0,
            "x": 0.23950924,
            "y": 0.391674548
        },
        {
            "key": "t",
            "lr": 1,
            "x": 0.09887997,
            "y": 0.404431283
        },
        {
            "key": "e",
            "lr": 0,
            "x": 0.382396936,
            "y": 0.0445570238
        },
        {
            "key": " ",
            "lr": 0,
            "x": -0.0153813288,
            "y": 0.582781434
        },
        {
            "key": "s",
            "lr": 1,
            "x": -0.208746612,
            "y": -0.9394818
        },
        {
            "key": "u",
            "lr": 0,
            "x": -0.2417066,
            "y": 0.009521775
        },
        {
            "key": "b",
            "lr": 1,
            "x": -0.476882219,
            "y": 0.108279675
        },
        {
            "key": "j",
            "lr": 1,
            "x": -0.18897061,
            "y": 0.09234901
        },
        {
            "key": "e",
            "lr": 1,
            "x": -0.06591998,
            "y": -0.09869686
        },
        {
            "key": "c",
            "lr": 0,
            "x": 0.112063967,
            "y": 0.200628683
        },
        {
            "key": "t",
            "lr": 0,
            "x": -0.07910398,
            "y": -0.213324383
        },
        {
            "key": "s",
            "lr": 1,
            "x": -0.3670156,
            "y": -0.222907171
        },
        {
            "key": " ",
            "lr": 0,
            "x": -0.153813288,
            "y": -0.146488845
        },
        {
            "key": "p",
            "lr": 1,
            "x": -0.008484146,
            "y": -1.0
        },
        {
            "key": "s",
            "lr": 1,
            "x": 0.5571459,
            "y": 0.830469668
        },
        {
            "key": "y",
            "lr": 1,
            "x": 0.214484081,
            "y": 0.9767754
        },
        {
            "key": "s",
            "lr": 1,
            "x": 0.343211144,
            "y": 0.939237654
        },
        {
            "key": "p",
            "lr": 1,
            "x": -0.314279616,
            "y": -0.6751305
        },
        {
            "key": "s",
            "lr": 1,
            "x": 0.5824152,
            "y": 0.722922444
        },
        {
            "key": "y",
            "lr": 0,
            "x": -0.2021546,
            "y": -0.12738426
        },
        {
            "key": "c",
            "lr": 1,
            "x": -0.1691946,
            "y": 0.09234901
        },
        {
            "key": "h",
            "lr": 0,
            "x": -0.0944853052,
            "y": -0.4745018
        },
        {
            "key": "o",
            "lr": 1,
            "x": 0.404553354,
            "y": 0.914517641
        },
        {
            "key": "h",
            "lr": 1,
            "x": -0.380199581,
            "y": -0.5636769
        },
        {
            "key": "o",
            "lr": 1,
            "x": -0.18897061,
            "y": -0.09869686
        },
        {
            "key": "l",
            "lr": 1,
            "x": 0.2725303,
            "y": 0.452223271
        },
        {
            "key": "o",
            "lr": 1,
            "x": 0.971404135,
            "y": 0.003173925
        },
        {
            "key": "g",
            "lr": 1,
            "x": 0.2285226,
            "y": 0.659199834
        },
        {
            "key": "y",
            "lr": 1,
            "x": -0.323068947,
            "y": -0.0222785119
        },
        {
            "key": "h",
            "lr": 1,
            "x": 0.7208472,
            "y": -0.60506
        },
        {
            "key": "i",
            "lr": 1,
            "x": -1.0,
            "y": 0.003112888
        },
        {
            "key": "s",
            "lr": 1,
            "x": -0.109866634,
            "y": -0.0541398376
        },
        {
            "key": " ",
            "lr": 1,
            "x": 0.08789331,
            "y": 0.6687826
        },
        {
            "key": "l",
            "lr": 0,
            "x": -0.193365276,
            "y": -0.0413831
        },
        {
            "key": "i",
            "lr": 1,
            "x": -0.126957,
            "y": -0.9919126
        },
        {
            "key": "b",
            "lr": 1,
            "x": 0.054933317,
            "y": 0.0382091738
        },
        {
            "key": "r",
            "lr": 1,
            "x": -0.0175786614,
            "y": 0.404431283
        },
        {
            "key": "a",
            "lr": 1,
            "x": -0.00219733268,
            "y": -0.3630482
        },
        {
            "key": "r",
            "lr": 0,
            "x": 0.204351917,
            "y": -0.108279675
        },
        {
            "key": "y",
            "lr": 0,
            "x": -0.85494554,
            "y": 0.23249
        },
        {
            "key": " ",
            "lr": 0,
            "x": 0.6021912,
            "y": 0.0445570238
        },
        {
            "key": "h",
            "lr": 1,
            "x": -0.6878872,
            "y": 0.0191045869
        },
        {
            "key": "a",
            "lr": 1,
            "x": -0.1472213,
            "y": -0.9681692
        },
        {
            "key": "s",
            "lr": 1,
            "x": 0.212652981,
            "y": 0.956694245
        },
        {
            "key": "a",
            "lr": 1,
            "x": 0.345042259,
            "y": 0.924771845
        },
        {
            "key": "h",
            "lr": 1,
            "x": -0.193365276,
            "y": -0.07641835
        },
        {
            "key": "a",
            "lr": 1,
            "x": 0.284127325,
            "y": 0.958830535
        },
        {
            "key": "h",
            "lr": 1,
            "x": -0.12524794,
            "y": 0.388500631
        },
        {
            "key": "a",
            "lr": 1,
            "x": -0.325205237,
            "y": -0.94570756
        },
        {
            "key": "s",
            "lr": 1,
            "x": -0.191167951,
            "y": -0.0126957
        },
        {
            "key": " ",
            "lr": 0,
            "x": -0.789025545,
            "y": 0.404431283
        },
        {
            "key": "m",
            "lr": 0,
            "x": -0.2417066,
            "y": 0.0445570238
        },
        {
            "key": "a",
            "lr": 1,
            "x": -0.145023957,
            "y": -0.984099865
        },
        {
            "key": "n",
            "lr": 1,
            "x": 0.186773255,
            "y": -0.0541398376
        },
        {
            "key": "y",
            "lr": 0,
            "x": -0.96481216,
            "y": 0.242011786
        },
        {
            "key": " ",
            "lr": 1,
            "x": 0.145023957,
            "y": -0.270699173
        },
        {
            "key": "b",
            "lr": 1,
            "x": -0.562639236,
            "y": 0.3471175
        },
        {
            "key": "o",
            "lr": 1,
            "x": 0.24579607,
            "y": 0.9693899
        },
        {
            "key": "b",
            "lr": 1,
            "x": 0.319589823,
            "y": 0.9475387
        },
        {
            "key": " ",
            "lr": 1,
            "x": 0.338450283,
            "y": -0.324839026
        },
        {
            "key": "b",
            "lr": 1,
            "x": -0.564836562,
            "y": 0.3471175
        },
        {
            "key": "o",
            "lr": 1,
            "x": -0.2033143,
            "y": -0.979155838
        },
        {
            "key": "o",
            "lr": 1,
            "x": -0.145023957,
            "y": -0.213324383
        },
        {
            "key": "k",
            "lr": 1,
            "x": 0.129642636,
            "y": 0.643330157
        },
        {
            "key": "s",
            "lr": 1,
            "x": 0.1010773,
            "y": 0.601886034
        },
        {
            "key": "s",
            "lr": 1,
            "x": 0.470290244,
            "y": 0.4076052
        }
    ],
    "inputSequence": [
        "t",
        "h",
        "i",
        "-thi, +this",
        " ",
        "c",
        "a",
        "m",
        "e",
        "r",
        "a",
        " ",
        "t",
        "a",
        "k",
        "e",
        "s",
        " ",
        "n",
        "i",
        "c",
        "-nic, +nice",
        " ",
        "p",
        "h",
        "o",
        "t",
        "o",
        "g",
        "r",
        "a",
        "-photogra, +photograph",
        " ",
        "Back",
        "s",
        "Enter",
        "p",
        "e",
        "Back",
        "r",
        "e",
        "r",
        "Back",
        "p",
        "a",
        "r",
        "e",
        " ",
        "f",
        "o",
        "r",
        " ",
        "t",
        "h",
        "e",
        " ",
        "e",
        "x",
        "a",
        "m",
        " ",
        "i",
        "n",
        " ",
        "a",
        "d",
        "v",
        "a",
        "n",
        "!",
        "Back",
        "c",
        "e",
        "Enter",
        "d",
        "a",
        "s",
        "h",
        "i",
        "n",
        "g",
        " ",
        "t",
        "h",
        "h",
        "Back",
        "r",
        "o",
        "i",
        "g",
        "j",
        "-throigj, +through",
        " ",
        "t",
        "h",
        "e",
        " ",
        "s",
        "m",
        "Back",
        "n",
        "o",
        "w",
        " ",
        "Enter",
        "Enter",
        "Back",
        "m",
        "y",
        " ",
        "f",
        "a",
        "v",
        "o",
        "7",
        "p",
        "Back",
        "Back",
        "e",
        "Back",
        "r",
        "i",
        "t",
        "e",
        " ",
        "s",
        "u",
        "b",
        "k",
        "e",
        "c",
        "-subkec, +subject",
        " ",
        "i",
        "s",
        "Enter",
        "p",
        "Back",
        "Back",
        " ",
        "p",
        "s",
        "y",
        "d",
        "Back",
        "c",
        "h",
        "o",
        "l",
        "o",
        "g",
        "-psycholog, +psychology",
        " ",
        "Enter",
        "t",
        "h",
        "i",
        "s",
        " ",
        "l",
        "i",
        "b",
        "r",
        "a",
        "r",
        "u",
        ":",
        "Back",
        "Back",
        "u",
        "Back",
        "y",
        " ",
        "h",
        "a",
        "s",
        " ",
        "m",
        "a",
        "b",
        "y",
        "Back",
        "Back",
        "n",
        "y",
        " ",
        "b",
        "o",
        "i",
        "o",
        "Back",
        "Back",
        "o",
        "m",
        "Back",
        "k",
        "d",
        "Back",
        "-book, +books",
        " "
    ]
}